em_mmt/__init__.py
em_mmt/em_mmt.py
em_mmt-0.3.6.dist-info/METADATA
em_mmt-0.3.6.dist-info/WHEEL
em_mmt-0.3.6.dist-info/RECORD
