Metadata-Version: 2.1
Name: em-mmt
Version: 0.3.6
Summary: This is a wrapper that combines Dynamic Time Warping and Casual Impact into one library.
Author: Marcus Hilliard
Author-email: marcus.hilliard@essencemediacom.com
Requires-Python: >=3.10,<4.0
Classifier: Programming Language :: Python :: 3
Classifier: Programming Language :: Python :: 3.10
Classifier: Programming Language :: Python :: 3.11
Classifier: Programming Language :: Python :: 3.12
Requires-Dist: datetime (>=5.5,<6.0)
Requires-Dist: dtw-python (>=1.4.2,<2.0.0)
Requires-Dist: matplotlib (>=3.8.4,<4.0.0)
Requires-Dist: numpy (>=1.26.4,<2.0.0)
Requires-Dist: pandas (>=2.2.2,<3.0.0)
Requires-Dist: pycausalimpact (>=0.1.1,<0.2.0)
Requires-Dist: scipy (>=1.13.0,<2.0.0)
Requires-Dist: tqdm (>=4.66.4,<5.0.0)
